passwordless/__init__.py
passwordless/client.py
passwordless/config.py
passwordless/errors.py
passwordless/models.py
passwordless/serialization.py
passwordless-2.0.0.dist-info/LICENSE
passwordless-2.0.0.dist-info/METADATA
passwordless-2.0.0.dist-info/WHEEL
passwordless-2.0.0.dist-info/RECORD
