Metadata-Version: 2.1
Name: passwordless
Version: 2.0.0
Summary: Passwordless.dev Python SDK
Home-page: https://bitwarden.com/products/passwordless
License: Apache-2.0
Keywords: passwordless,bitwarden
Author: Bitwarden
Author-email: hello@bitwarden.com
Maintainer: Maciej Zieniuk
Maintainer-email: zieniuk.maciej@gmail.com
Requires-Python: >=3.9
Classifier: Development Status :: 5 - Production/Stable
Classifier: Intended Audience :: Developers
Classifier: License :: OSI Approved :: Apache Software License
Classifier: Programming Language :: Python :: 3
Classifier: Programming Language :: Python :: 3.9
Classifier: Programming Language :: Python :: 3.10
Classifier: Programming Language :: Python :: 3.11
Classifier: Programming Language :: Python :: 3.12
Classifier: Topic :: Communications :: FIDO
Classifier: Topic :: Internet :: WWW/HTTP
Classifier: Topic :: Security
Classifier: Topic :: Software Development :: Libraries
Requires-Dist: marshmallow (>=3,<4)
Requires-Dist: python-dateutil (>=2,<3)
Requires-Dist: requests (>=2,<3)
Project-URL: Documentation, https://docs.passwordless.dev/guide
